setup.py
dcef/__init__.py
dcef/_frontend.py
dcef/_version.py
dcef/all_transforms.py
dcef/configure_utils.py
dcef/dcef_widget.py
dcef/dcf_transform.py
dcef/df_methods.py
dcef/lispy.py
dcef/summary_stats.py
dcef/views.py
dcef/labextension/package.json
dcef/labextension/static/116.f2c748ce51e22b52b0cb.js
dcef/labextension/static/116.f2c748ce51e22b52b0cb.js.LICENSE.txt
dcef/labextension/static/250.ca3c9f855fbc1747d0ae.js
dcef/labextension/static/250.ca3c9f855fbc1747d0ae.js.LICENSE.txt
dcef/labextension/static/480.ccd73b95e569f66845e5.js
dcef/labextension/static/486.0708227d0a518f636636.js
dcef/labextension/static/486.0708227d0a518f636636.js.LICENSE.txt
dcef/labextension/static/568.b3c25a51cdf2e2d0b274.js
dcef/labextension/static/remoteEntry.efed5e74bfbc9c4fdfb8.js
dcef/labextension/static/style.js
dcef/labextension/static/third-party-licenses.json
dcef/nbextension/index.js
dcef/nbextension/index.js.LICENSE.txt
docs/source/conf.py
ranch_hand-0.2.5.data/data/share/jupyter/labextensions/dcef/package.json
ranch_hand-0.2.5.data/data/share/jupyter/labextensions/dcef/static/116.f2c748ce51e22b52b0cb.js
ranch_hand-0.2.5.data/data/share/jupyter/labextensions/dcef/static/116.f2c748ce51e22b52b0cb.js.LICENSE.txt
ranch_hand-0.2.5.data/data/share/jupyter/labextensions/dcef/static/250.ca3c9f855fbc1747d0ae.js
ranch_hand-0.2.5.data/data/share/jupyter/labextensions/dcef/static/250.ca3c9f855fbc1747d0ae.js.LICENSE.txt
ranch_hand-0.2.5.data/data/share/jupyter/labextensions/dcef/static/480.ccd73b95e569f66845e5.js
ranch_hand-0.2.5.data/data/share/jupyter/labextensions/dcef/static/486.0708227d0a518f636636.js
ranch_hand-0.2.5.data/data/share/jupyter/labextensions/dcef/static/486.0708227d0a518f636636.js.LICENSE.txt
ranch_hand-0.2.5.data/data/share/jupyter/labextensions/dcef/static/568.b3c25a51cdf2e2d0b274.js
ranch_hand-0.2.5.data/data/share/jupyter/labextensions/dcef/static/remoteEntry.efed5e74bfbc9c4fdfb8.js
ranch_hand-0.2.5.data/data/share/jupyter/labextensions/dcef/static/style.js
ranch_hand-0.2.5.dist-info/METADATA
ranch_hand-0.2.5.dist-info/WHEEL
ranch_hand-0.2.5.dist-info/licenses/LICENSE.txt
ranch_hand-0.2.5.dist-info/RECORD
